{
    "_checkpoint": {
        "global_record": {},
        "progress": [
            7,
            30
        ],
        "records": [
            {
                "index": 0,
                "infractions": {
                    "collisions_layout": [],
                    "collisions_pedestrian": [],
                    "collisions_vehicle": [],
                    "outside_route_lanes": [],
                    "red_light": [],
                    "route_dev": [],
                    "route_timeout": [],
                    "stop_infraction": [],
                    "vehicle_blocked": []
                },
                "meta": {
                    "duration_game": 62.9500009380281,
                    "duration_system": 252.77266478538513,
                    "route_length": 1071.0281341479306,
                    "total_steps": 1258
                },
                "route_id": "RouteScenario_16",
                "scores": {
                    "score_composed": 0.0,
                    "score_penalty": 1.0,
                    "score_route": 0.0
                },
                "status": "Failed"
            },
            {
                "index": 1,
                "infractions": {
                    "collisions_layout": [],
                    "collisions_pedestrian": [],
                    "collisions_vehicle": [],
                    "outside_route_lanes": [],
                    "red_light": [],
                    "route_dev": [],
                    "route_timeout": [],
                    "stop_infraction": [],
                    "vehicle_blocked": []
                },
                "meta": {
                    "duration_game": 104.85000156238675,
                    "duration_system": 424.8742187023163,
                    "route_length": 1071.0281341479306,
                    "total_steps": 2096
                },
                "route_id": "RouteScenario_16",
                "scores": {
                    "score_composed": 0.0,
                    "score_penalty": 1.0,
                    "score_route": 0.0
                },
                "status": "Failed"
            },
            {
                "index": 2,
                "infractions": {
                    "collisions_layout": [],
                    "collisions_pedestrian": [],
                    "collisions_vehicle": [],
                    "outside_route_lanes": [],
                    "red_light": [],
                    "route_dev": [],
                    "route_timeout": [],
                    "stop_infraction": [],
                    "vehicle_blocked": []
                },
                "meta": {
                    "duration_game": 13.800000205636024,
                    "duration_system": 55.171666383743286,
                    "route_length": 1071.0281341479306,
                    "total_steps": 275
                },
                "route_id": "RouteScenario_16",
                "scores": {
                    "score_composed": 0.0,
                    "score_penalty": 1.0,
                    "score_route": 0.0
                },
                "status": "Failed"
            },
            {
                "index": 3,
                "infractions": {
                    "collisions_layout": [],
                    "collisions_pedestrian": [],
                    "collisions_vehicle": [],
                    "outside_route_lanes": [],
                    "red_light": [],
                    "route_dev": [],
                    "route_timeout": [],
                    "stop_infraction": [],
                    "vehicle_blocked": []
                },
                "meta": {
                    "duration_game": 0.45000000670552254,
                    "duration_system": 1.681990385055542,
                    "route_length": 862.4300893683893,
                    "total_steps": 8
                },
                "route_id": "RouteScenario_17",
                "scores": {
                    "score_composed": 0.0,
                    "score_penalty": 1.0,
                    "score_route": 0
                },
                "status": "Failed"
            },
            {
                "index": 4,
                "infractions": {
                    "collisions_layout": [],
                    "collisions_pedestrian": [],
                    "collisions_vehicle": [],
                    "outside_route_lanes": [],
                    "red_light": [],
                    "route_dev": [],
                    "route_timeout": [],
                    "stop_infraction": [],
                    "vehicle_blocked": []
                },
                "meta": {
                    "duration_game": 0.30000000447034836,
                    "duration_system": 1.1237547397613525,
                    "route_length": 862.4300893683893,
                    "total_steps": 5
                },
                "route_id": "RouteScenario_17",
                "scores": {
                    "score_composed": 0.0,
                    "score_penalty": 1.0,
                    "score_route": 0
                },
                "status": "Failed"
            },
            {
                "index": 5,
                "infractions": {
                    "collisions_layout": [],
                    "collisions_pedestrian": [],
                    "collisions_vehicle": [],
                    "outside_route_lanes": [],
                    "red_light": [],
                    "route_dev": [],
                    "route_timeout": [],
                    "stop_infraction": [],
                    "vehicle_blocked": []
                },
                "meta": {
                    "duration_game": 28.10000041872263,
                    "duration_system": 113.01982808113098,
                    "route_length": 862.4300893683893,
                    "total_steps": 561
                },
                "route_id": "RouteScenario_17",
                "scores": {
                    "score_composed": 0.0,
                    "score_penalty": 1.0,
                    "score_route": 0
                },
                "status": "Failed"
            },
            {
                "index": 6,
                "infractions": {
                    "collisions_layout": [],
                    "collisions_pedestrian": [],
                    "collisions_vehicle": [],
                    "outside_route_lanes": [],
                    "red_light": [],
                    "route_dev": [],
                    "route_timeout": [],
                    "stop_infraction": [],
                    "vehicle_blocked": []
                },
                "meta": {
                    "duration_game": 13.850000206381083,
                    "duration_system": 311.7614860534668,
                    "route_length": 1018.1548091661475,
                    "total_steps": 276
                },
                "route_id": "RouteScenario_18",
                "scores": {
                    "score_composed": 0.0,
                    "score_penalty": 1.0,
                    "score_route": 0
                },
                "status": "Failed"
            }
        ]
    },
    "eligible": false,
    "entry_status": "Started",
    "labels": [],
    "sensors": [
        "carla_camera",
        "carla_camera",
        "carla_imu",
        "carla_gnss",
        "carla_speedometer"
    ],
    "values": []
}